setup.py
cache/__init__.py
cache/jsonr.py
cache/pickler.py
cacher.egg-info/PKG-INFO
cacher.egg-info/SOURCES.txt
cacher.egg-info/dependency_links.txt
cacher.egg-info/requires.txt
cacher.egg-info/top_level.txt