Metadata-Version: 1.0
Name: cacher
Version: 0.1
Summary: A simple key-value cache frontend that can be used with different backends
Home-page: https://github.com/legoktm/cacher
Author: Kunal Mehta
Author-email: legoktm@gmail.com
License: MIT License
Platform: UNKNOWN
